openwarehouse/__about__.py
openwarehouse/__init__.py
openwarehouse-0.0.1.dist-info/METADATA
openwarehouse-0.0.1.dist-info/WHEEL
openwarehouse-0.0.1.dist-info/licenses/LICENSE.txt
openwarehouse-0.0.1.dist-info/RECORD
