Metadata-Version: 2.1
Name: openwarehouse
Version: 0.0.1
Project-URL: Documentation, https://github.com/marcelblijleven/openwarehouse#readme
Project-URL: Issues, https://github.com/marcelblijleven/openwarehouse/issues
Project-URL: Source, https://github.com/marcelblijleven/openwarehouse
Author-email: Marcel Blijleven <marcelblijleven@gmail.com>
License-Expression: MIT
License-File: LICENSE.txt
Classifier: Development Status :: 4 - Beta
Classifier: Programming Language :: Python
Classifier: Programming Language :: Python :: 3.9
Classifier: Programming Language :: Python :: 3.10
Classifier: Programming Language :: Python :: 3.11
Classifier: Programming Language :: Python :: Implementation :: CPython
Classifier: Programming Language :: Python :: Implementation :: PyPy
Requires-Python: >=3.9
